LICENSE
README.md
memvid_sdk/__init__.py
memvid_sdk/_analytics.py
memvid_sdk/_lib.abi3.so
memvid_sdk/_registry.py
memvid_sdk/_sentinel.py
memvid_sdk/adapters/__init__.py
memvid_sdk/adapters/autogen.py
memvid_sdk/adapters/crewai.py
memvid_sdk/adapters/google_adk.py
memvid_sdk/adapters/haystack.py
memvid_sdk/adapters/langchain.py
memvid_sdk/adapters/langgraph.py
memvid_sdk/adapters/llamaindex.py
memvid_sdk/adapters/mcp.py
memvid_sdk/adapters/openai.py
memvid_sdk/adapters/semantic_kernel.py
memvid_sdk/adapters/vercel_ai.py
memvid_sdk/clip.py
memvid_sdk/documents/__init__.py
memvid_sdk/documents/docx.py
memvid_sdk/documents/pdf.py
memvid_sdk/documents/pptx.py
memvid_sdk/documents/xlsx.py
memvid_sdk/embeddings.py
memvid_sdk/entities.py
memvid_sdk/types.py
memvid_sdk-2.0.148.dist-info/METADATA
memvid_sdk-2.0.148.dist-info/WHEEL
memvid_sdk-2.0.148.dist-info/licenses/LICENSE
memvid_sdk-2.0.148.dist-info/RECORD
