Metadata-Version: 2.4
Name: memvid-sdk
Version: 2.0.148
Classifier: Programming Language :: Python
Classifier: Programming Language :: Python :: 3
Classifier: Programming Language :: Python :: 3 :: Only
Classifier: Programming Language :: Python :: Implementation :: CPython
Classifier: Operating System :: OS Independent
Classifier: License :: OSI Approved :: Apache Software License
Classifier: Topic :: Scientific/Engineering :: Artificial Intelligence
Classifier: Topic :: Database
Classifier: Intended Audience :: Developers
Requires-Dist: typing-extensions>=4.0.0
Requires-Dist: autogen-agentchat>=0.4,<1.0 ; extra == 'autogen'
Requires-Dist: crewai>=0.70,<3.0 ; extra == 'crewai'
Requires-Dist: pypdf>=4.0,<7.0 ; extra == 'documents'
Requires-Dist: openpyxl>=3.1,<4.0 ; extra == 'documents'
Requires-Dist: python-pptx>=1.0,<2.0 ; extra == 'documents'
Requires-Dist: python-docx>=1.1,<2.0 ; extra == 'documents'
Requires-Dist: langchain-core>=0.3,<3.0 ; extra == 'full'
Requires-Dist: llama-index>=0.12,<1.0 ; extra == 'full'
Requires-Dist: openai>=1.0,<3.0 ; extra == 'full'
Requires-Dist: crewai>=0.70,<3.0 ; extra == 'full'
Requires-Dist: ai>=4.0,<6.0 ; extra == 'full'
Requires-Dist: autogen-agentchat>=0.4,<1.0 ; extra == 'full'
Requires-Dist: haystack-ai>=2.8,<4.0 ; extra == 'full'
Requires-Dist: langgraph>=0.2,<3.0 ; extra == 'full'
Requires-Dist: semantic-kernel>=1.17,<2.0 ; extra == 'full'
Requires-Dist: pypdf>=4.0,<7.0 ; extra == 'full'
Requires-Dist: openpyxl>=3.1,<4.0 ; extra == 'full'
Requires-Dist: python-pptx>=1.0,<2.0 ; extra == 'full'
Requires-Dist: python-docx>=1.1,<2.0 ; extra == 'full'
Requires-Dist: haystack-ai>=2.8,<4.0 ; extra == 'haystack'
Requires-Dist: langchain-core>=0.3,<3.0 ; extra == 'langchain'
Requires-Dist: langgraph>=0.2,<3.0 ; extra == 'langgraph'
Requires-Dist: llama-index>=0.12,<1.0 ; extra == 'llamaindex'
Requires-Dist: openai>=1.0,<3.0 ; extra == 'openai'
Requires-Dist: semantic-kernel>=1.17,<2.0 ; extra == 'semantic-kernel'
Requires-Dist: ai>=4.0,<6.0 ; extra == 'vercel-ai'
Provides-Extra: autogen
Provides-Extra: crewai
Provides-Extra: documents
Provides-Extra: full
Provides-Extra: haystack
Provides-Extra: langchain
Provides-Extra: langgraph
Provides-Extra: llamaindex
Provides-Extra: openai
Provides-Extra: semantic-kernel
Provides-Extra: vercel-ai
License-File: LICENSE
Summary: Single-file AI memory system for Python. Store, search, and query documents with built-in RAG.
Keywords: ai,memory,rag,vector-search,semantic-search,langchain,llamaindex,embeddings
Author: Memvid Inc.
License: Apache-2.0
Requires-Python: >=3.8
Project-URL: Documentation, https://docs.memvid.com
Project-URL: Homepage, https://memvid.com
Project-URL: Repository, https://github.com/memvid/memvid
